ssbc/__init__.py
ssbc/__main__.py
ssbc/_logging.py
ssbc/cli.py
ssbc/hyperparameter.py
ssbc/mcp_server.py
ssbc/simulation.py
ssbc/utils.py
ssbc/validation.py
ssbc/validation_math.py
ssbc/bounds/__init__.py
ssbc/bounds/statistical.py
ssbc/calibration/__init__.py
ssbc/calibration/bootstrap.py
ssbc/calibration/conformal.py
ssbc/calibration/cross_conformal.py
ssbc/core_pkg/__init__.py
ssbc/core_pkg/core.py
ssbc/metrics/__init__.py
ssbc/metrics/loo_uncertainty.py
ssbc/metrics/operational_bounds_simple.py
ssbc/reporting/__init__.py
ssbc/reporting/rigorous_report.py
ssbc/reporting/visualization.py
ssbc/validation_pkg/__init__.py
ssbc-1.4.0.dist-info/licenses/LICENSE
ssbc-1.4.0.dist-info/METADATA
ssbc-1.4.0.dist-info/WHEEL
ssbc-1.4.0.dist-info/entry_points.txt
ssbc-1.4.0.dist-info/top_level.txt
ssbc-1.4.0.dist-info/RECORD
