Metadata-Version: 2.4
Name: ssbc
Version: 1.4.0
Summary: Small Sample Beta Correction - PAC guarantees with small datasets
Author-email: Petrus H Zwart <phzwart@lbl.gov>
Maintainer-email: Petrus H Zwart <phzwart@lbl.gov>
License: BSD License
Project-URL: bugs, https://github.com/phzwart/ssbc/issues
Project-URL: changelog, https://github.com/phzwart/ssbc/blob/master/changelog.md
Project-URL: homepage, https://github.com/phzwart/ssbc
Classifier: Development Status :: 4 - Beta
Classifier: Intended Audience :: Science/Research
Classifier: Intended Audience :: Developers
Classifier: Programming Language :: Python :: 3
Classifier: Programming Language :: Python :: 3.10
Classifier: Programming Language :: Python :: 3.11
Classifier: Programming Language :: Python :: 3.12
Classifier: Programming Language :: Python :: 3.13
Classifier: Topic :: Scientific/Engineering
Classifier: Topic :: Scientific/Engineering :: Mathematics
Classifier: Topic :: Software Development :: Libraries :: Python Modules
Requires-Python: >=3.10
License-File: LICENSE
Requires-Dist: joblib
Requires-Dist: matplotlib
Requires-Dist: numpy
Requires-Dist: pandas
Requires-Dist: plotly
Requires-Dist: rich
Requires-Dist: scipy
Requires-Dist: typer
Provides-Extra: test
Requires-Dist: coverage; extra == "test"
Requires-Dist: pytest; extra == "test"
Requires-Dist: pytest-cov; extra == "test"
Requires-Dist: ruff; extra == "test"
Requires-Dist: ty; extra == "test"
Requires-Dist: ipdb; extra == "test"
Provides-Extra: dev
Requires-Dist: pre-commit; extra == "dev"
Requires-Dist: bandit[toml]; extra == "dev"
Provides-Extra: docs
Requires-Dist: sphinx>=7.0; extra == "docs"
Requires-Dist: sphinx-rtd-theme; extra == "docs"
Requires-Dist: myst-parser; extra == "docs"
Provides-Extra: mcp
Requires-Dist: fastmcp; extra == "mcp"
Dynamic: license-file
